cmo_dataloader/__init__.py
cmo_dataloader/resources.py
cmo_dataloader/database/__init__.py
cmo_dataloader/database/load_db.py
cmo_dataloader/files/__init__.py
cmo_dataloader/files/load_flat_files.py
cmo_dataloader-0.1.0.dist-info/METADATA
cmo_dataloader-0.1.0.dist-info/WHEEL
cmo_dataloader-0.1.0.dist-info/top_level.txt
cmo_dataloader-0.1.0.dist-info/RECORD
