Metadata-Version: 2.1
Name: cmo-dataloader
Version: 0.1.0
Summary: Load a bulk of data from flat files or databases at once
Home-page: https://dev.azure.com/Cmotions/Packages/_git/cmo_dataloader
Author: Jeanine Schoonemann
Author-email: service@cmotions.nl
License: UNKNOWN
Platform: UNKNOWN
Requires-Python: >=3.6
Requires-Dist: chardet (>=3.0.4)
Requires-Dist: clevercsv (>=0.6.3)
Requires-Dist: cmo-databaseutils
Provides-Extra: dev
Requires-Dist: black ; extra == 'dev'
Requires-Dist: ipykernel ; extra == 'dev'
Requires-Dist: jupyterlab ; extra == 'dev'
Requires-Dist: pytest (>=6.2.4) ; extra == 'dev'
Requires-Dist: python-dotenv ; extra == 'dev'
Requires-Dist: twine ; extra == 'dev'
